{
    "_id": {
        "$oid": "5e21ea5a63e5671d1c4a614f"
    },
    "likes": {
        "$numberInt": "102"
    },
    "rating": {
        "$numberInt": "4"
    },
    "name": "Lincoln MKZ",
    "price": {
        "$numberInt": "55780"
    },
    "imageUrl": "https://images.pexels.com/photos/627678/pexels-photo-627678.jpeg?auto=compress&cs=tinysrgb&dpr=2&h=750&w=1260",
    "description": "Intended to preserve the greatest of luxuries, your time, Lincoln ownership includes the pickup and delivery* of your vehicle for all your service or maintenance needs, as well as a Lincoln Loaner™ until service is completed.",
    "features": "REFINED POWER AT YOUR CONTROL. An available twin-turbocharged 3.0L V6 engine produces 400 horsepower* and an exhilarating driving experience. A number of features, including an adaptive suspension and Dynamic Torque vectoring,** help to harness and control power, creating an even more fluid driving experience.",
    "category": "Sedan",
    "mileages": "28000",
    "createdDate": {
        "$date": {
            "$numberLong": "1579280986603"
        }
    },
    "__v": {
        "$numberInt": "0"
    }
} 

